h2d/__init__.py
h2d/converter.py
h2d-0.1.1.dist-info/LICENSE
h2d-0.1.1.dist-info/METADATA
h2d-0.1.1.dist-info/WHEEL
h2d-0.1.1.dist-info/top_level.txt
h2d-0.1.1.dist-info/RECORD
