Metadata-Version: 2.1
Name: h2d
Version: 0.1.1
Summary: 轻松将您的html转为docx格式
Home-page: https://github.com/zzzyansong/h2d
Author: zzzyansong
Author-email: i@zhuyansong.com
License: MIT
Classifier: Programming Language :: Python :: 3
Classifier: Programming Language :: Python :: 3.6
Classifier: Programming Language :: Python :: 3.7
Classifier: Programming Language :: Python :: 3.8
Classifier: Programming Language :: Python :: 3.9
Classifier: Programming Language :: Python :: 3.10
Classifier: Programming Language :: Python :: 3.11
Classifier: Programming Language :: Python :: 3.12
Classifier: License :: OSI Approved :: MIT License
Classifier: Operating System :: OS Independent
Requires-Python: >=3.6
License-File: LICENSE
Requires-Dist: python-docx >=0.8.11
Requires-Dist: requests >=2.28.0
Requires-Dist: beautifulsoup4 >=4.12.0
Requires-Dist: cssutils >=2.7.1
